rhizonet/__init__.py
rhizonet/_version.py
rhizonet/metrics.py
rhizonet/postprocessing.py
rhizonet/predict.py
rhizonet/prepare_patches.py
rhizonet/simpleLogger.py
rhizonet/train.py
rhizonet/unet2D.py
rhizonet/utils.py
rhizonet-0.0.21.dist-info/AUTHORS.md
rhizonet-0.0.21.dist-info/LICENSE
rhizonet-0.0.21.dist-info/METADATA
rhizonet-0.0.21.dist-info/WHEEL
rhizonet-0.0.21.dist-info/entry_points.txt
rhizonet-0.0.21.dist-info/top_level.txt
rhizonet-0.0.21.dist-info/RECORD
