Metadata-Version: 2.1
Name: rhizonet
Version: 0.0.21
Summary: Segmentation pipeline for EcoFAB images
Home-page: https://github.com/lbl-camera/rhizonet
Author: Zineb Sordo, Daniela Ushizima, Peter Andeer, James Sethian and Trent Northen.
Author-email: zsordo@lbl.gov
License: MIT license
Keywords: rhizonet
Classifier: Development Status :: 2 - Pre-Alpha
Classifier: Natural Language :: English
Classifier: Programming Language :: Python :: 3
Requires-Python: >=3.8
License-File: LICENSE
License-File: AUTHORS.md
Requires-Dist: versioneer
Requires-Dist: wheel
Requires-Dist: cachetools ==5.3.1
Requires-Dist: constants ==0.6.0
Requires-Dist: contourpy ==1.1.1
Requires-Dist: einops ==0.8.0
Requires-Dist: graphviz ==0.20.1
Requires-Dist: imageio ==2.31.5
Requires-Dist: imagecodecs
Requires-Dist: joblib ==1.3.2
Requires-Dist: lightning ==2.0.9.post0
Requires-Dist: lightning-cloud ==0.5.39
Requires-Dist: lightning-utilities ==0.9.0
Requires-Dist: matplotlib
Requires-Dist: monai ==1.3.2
Requires-Dist: neptune ==1.8.1
Requires-Dist: nibabel ==5.2.1
Requires-Dist: numpy
Requires-Dist: opencv-python ==4.8.1.78
Requires-Dist: pandas
Requires-Dist: Pillow ==9.3.0
Requires-Dist: pytorch-lightning ==2.0.9.post0
Requires-Dist: scikit-image ==0.19.3
Requires-Dist: scikit-learn ==1.3.1
Requires-Dist: tensorboard
Requires-Dist: torch ==2.4.1
Requires-Dist: torchaudio ==2.4.1
Requires-Dist: torchdata ==0.8.0
Requires-Dist: torchmetrics ==1.2.0
Requires-Dist: torchtext ==0.18.0
Requires-Dist: torchvision ==0.19.1
Requires-Dist: torchviz ==0.0.2
Requires-Dist: tqdm ==4.66.1
Requires-Dist: wandb ==0.18.3
Provides-Extra: docs
Requires-Dist: sphinx ; extra == 'docs'
Requires-Dist: sphinx-rtd-theme ; extra == 'docs'
Requires-Dist: myst-parser ; extra == 'docs'
Requires-Dist: myst-nb ; extra == 'docs'
Requires-Dist: sphinx-panels ; extra == 'docs'
Requires-Dist: autodocs ; extra == 'docs'
Provides-Extra: tests
Requires-Dist: pytest ; extra == 'tests'
Requires-Dist: codecov ; extra == 'tests'
Requires-Dist: pytest-cov ; extra == 'tests'
